{
  "meta": {
    "accepted_with_shortfall": false,
    "attempts_total": 50,
    "elapsed_total_s": 0.0753786563873291,
    "found": 50,
    "group": "panda_arm",
    "ik_successes_total": 50,
    "ik_timeout_s": 0.1,
    "named_start_for_seeding": "ready",
    "nullspace_jitter": 0.02,
    "nullspace_step": 0.2,
    "num_spaces": 10,
    "pass_metas": [
      {
        "attempts": 50,
        "elapsed_s": 0.07527375221252441,
        "found": 50,
        "group": "panda_arm",
        "ik_successes": 50,
        "ik_timeout_s": 0.1,
        "named_start_for_seeding": "ready",
        "nullspace_jitter": 0.02,
        "nullspace_step": 0.2,
        "num_spaces": 10,
        "pass_index": 0,
        "requested": 50,
        "rng": {
          "deterministic_joint_seeds": true,
          "engine": "numpy.default_rng",
          "note": "Avoid MoveIt internal RNG (RobotState.set_to_random_positions)."
        },
        "seed": 2001007,
        "seed_pass": 2001007,
        "target_point": {
          "x": 0.4474597967895352,
          "y": 0.07414919572539724,
          "z": 0.09897098197944355
        },
        "tip_link": "panda_link8",
        "uniq_resolution_rad": 0.001,
        "yaw_range_rad": 6.283185307179586
      }
    ],
    "pass_seed_stride": 100000,
    "passes_requested": 3,
    "passes_used": 1,
    "precheck_attempts": 50,
    "precheck_found": 50,
    "precheck_ik_successes": 50,
    "precheck_max_attempts": 1200,
    "precheck_num_spaces": 8,
    "reason": "ok",
    "requested": 50,
    "resample_max": 200,
    "resample_trial_final": 1,
    "resample_trials_used": 1,
    "seed": 2001007,
    "shortfall": 0,
    "target_point": {
      "x": 0.4474597967895352,
      "y": 0.07414919572539724,
      "z": 0.09897098197944355
    },
    "tip_link": "panda_link8",
    "uniq_resolution_rad": 0.001,
    "yaw_range_rad": 6.283185307179586
  },
  "solutions": [
    {
      "attempt": 1,
      "attempt_global": 1,
      "index": 0,
      "joint_names": [
        "panda_joint1",
        "panda_joint2",
        "panda_joint3",
        "panda_joint4",
        "panda_joint5",
        "panda_joint6",
        "panda_joint7"
      ],
      "joint_positions": [
        1.7577583563606622,
        -1.7628,
        -1.8435645940231435,
        -2.3698911439741654,
        -1.8996705053647314,
        1.618457630979215,
        -1.3264846906388332
      ],
      "pass_index": 0,
      "pass_seed": 2001007,
      "sampled_yaw_rad": -3.131878072832554,
      "target_point": {
        "x": 0.4474597967895352,
        "y": 0.07414919572539724,
        "z": 0.09897098197944355
      },
      "tip_link": "panda_link8"
    },
    {
      "attempt": 2,
      "attempt_global": 2,
      "index": 1,
      "joint_names": [
        "panda_joint1",
        "panda_joint2",
        "panda_joint3",
        "panda_joint4",
        "panda_joint5",
        "panda_joint6",
        "panda_joint7"
      ],
      "joint_positions": [
        -0.7956122333658959,
        0.747707423642151,
        0.7738911206734694,
        -2.3699972181959903,
        -1.2409545805575248,
        2.6153154604002924,
        -1.3269232372344004
      ],
      "pass_index": 0,
      "pass_seed": 2001007,
      "sampled_yaw_rad": -3.131878072832554,
      "target_point": {
        "x": 0.4474597967895352,
        "y": 0.07414919572539724,
        "z": 0.09897098197944355
      },
      "tip_link": "panda_link8"
    },
    {
      "attempt": 3,
      "attempt_global": 3,
      "index": 2,
      "joint_names": [
        "panda_joint1",
        "panda_joint2",
        "panda_joint3",
        "panda_joint4",
        "panda_joint5",
        "panda_joint6",
        "panda_joint7"
      ],
      "joint_positions": [
        1.8234935159233903,
        -1.555398615646852,
        -1.8884368979025943,
        -2.35887456171309,
        -1.7889375046958707,
        1.8040513340652775,
        -1.2829112703921788
      ],
      "pass_index": 0,
      "pass_seed": 2001007,
      "sampled_yaw_rad": -3.131878072832554,
      "target_point": {
        "x": 0.4474597967895352,
        "y": 0.07414919572539724,
        "z": 0.09897098197944355
      },
      "tip_link": "panda_link8"
    },
    {
      "attempt": 4,
      "attempt_global": 4,
      "index": 3,
      "joint_names": [
        "panda_joint1",
        "panda_joint2",
        "panda_joint3",
        "panda_joint4",
        "panda_joint5",
        "panda_joint6",
        "panda_joint7"
      ],
      "joint_positions": [
        1.818502106570566,
        -1.5701932122341287,
        -1.8846575644443506,
        -2.3595377530070873,
        -1.7967119415619126,
        1.790565496932448,
        -1.2854960070683834
      ],
      "pass_index": 0,
      "pass_seed": 2001007,
      "sampled_yaw_rad": -3.131878072832554,
      "target_point": {
        "x": 0.4474597967895352,
        "y": 0.07414919572539724,
        "z": 0.09897098197944355
      },
      "tip_link": "panda_link8"
    },
    {
      "attempt": 5,
      "attempt_global": 5,
      "index": 4,
      "joint_names": [
        "panda_joint1",
        "panda_joint2",
        "panda_joint3",
        "panda_joint4",
        "panda_joint5",
        "panda_joint6",
        "panda_joint7"
      ],
      "joint_positions": [
        1.8379760389903936,
        -1.5134576578265746,
        -1.8996701728743475,
        -2.357100234703078,
        -1.766924312026681,
        1.8424830153608047,
        -1.2760190672025251
      ],
      "pass_index": 0,
      "pass_seed": 2001007,
      "sampled_yaw_rad": -3.131878072832554,
      "target_point": {
        "x": 0.4474597967895352,
        "y": 0.07414919572539724,
        "z": 0.09897098197944355
      },
      "tip_link": "panda_link8"
    },
    {
      "attempt": 6,
      "attempt_global": 6,
      "index": 5,
      "joint_names": [
        "panda_joint1",
        "panda_joint2",
        "panda_joint3",
        "panda_joint4",
        "panda_joint5",
        "panda_joint6",
        "panda_joint7"
      ],
      "joint_positions": [
        -1.3838260479846995,
        1.7628,
        1.2980365529419526,
        -2.369894482188127,
        -1.8996655057244378,
        1.6184471802273035,
        -0.397022157007197
      ],
      "pass_index": 0,
      "pass_seed": 2001007,
      "sampled_yaw_rad": -2.202436048921838,
      "target_point": {
        "x": 0.4474597967895352,
        "y": 0.07414919572539724,
        "z": 0.09897098197944355
      },
      "tip_link": "panda_link8"
    },
    {
      "attempt": 7,
      "attempt_global": 7,
      "index": 6,
      "joint_names": [
        "panda_joint1",
        "panda_joint2",
        "panda_joint3",
        "panda_joint4",
        "panda_joint5",
        "panda_joint6",
        "panda_joint7"
      ],
      "joint_positions": [
        2.8973,
        -0.5332648247132231,
        -2.8555022419412315,
        -2.4439415866541383,
        -0.674307997896282,
        2.909752790400501,
        -0.7525082606899821
      ],
      "pass_index": 0,
      "pass_seed": 2001007,
      "sampled_yaw_rad": -2.202436048921838,
      "target_point": {
        "x": 0.4474597967895352,
        "y": 0.07414919572539724,
        "z": 0.09897098197944355
      },
      "tip_link": "panda_link8"
    },
    {
      "attempt": 8,
      "attempt_global": 8,
      "index": 7,
      "joint_names": [
        "panda_joint1",
        "panda_joint2",
        "panda_joint3",
        "panda_joint4",
        "panda_joint5",
        "panda_joint6",
        "panda_joint7"
      ],
      "joint_positions": [
        1.7577602349368218,
        -1.7628,
        -1.843564147634465,
        -2.3698877396896094,
        -1.8996691705138138,
        1.6184595388771275,
        -0.39704078987176766
      ],
      "pass_index": 0,
      "pass_seed": 2001007,
      "sampled_yaw_rad": -2.202436048921838,
      "target_point": {
        "x": 0.4474597967895352,
        "y": 0.07414919572539724,
        "z": 0.09897098197944355
      },
      "tip_link": "panda_link8"
    },
    {
      "attempt": 9,
      "attempt_global": 9,
      "index": 8,
      "joint_names": [
        "panda_joint1",
        "panda_joint2",
        "panda_joint3",
        "panda_joint4",
        "panda_joint5",
        "panda_joint6",
        "panda_joint7"
      ],
      "joint_positions": [
        -0.06828408753387791,
        0.5075803247281648,
        0.1533847962105959,
        -2.469416277649689,
        -0.4155140882085222,
        2.9565651278859986,
        -0.942232721908503
      ],
      "pass_index": 0,
      "pass_seed": 2001007,
      "sampled_yaw_rad": -2.202436048921838,
      "target_point": {
        "x": 0.4474597967895352,
        "y": 0.07414919572539724,
        "z": 0.09897098197944355
      },
      "tip_link": "panda_link8"
    },
    {
      "attempt": 10,
      "attempt_global": 10,
      "index": 9,
      "joint_names": [
        "panda_joint1",
        "panda_joint2",
        "panda_joint3",
        "panda_joint4",
        "panda_joint5",
        "panda_joint6",
        "panda_joint7"
      ],
      "joint_positions": [
        -1.3503224726653704,
        1.6538244121316243,
        1.2765855187181403,
        -2.3636494801403707,
        -1.8409035674902505,
        1.7150344604106431,
        -0.3721675687060653
      ],
      "pass_index": 0,
      "pass_seed": 2001007,
      "sampled_yaw_rad": -2.202436048921838,
      "target_point": {
        "x": 0.4474597967895352,
        "y": 0.07414919572539724,
        "z": 0.09897098197944355
      },
      "tip_link": "panda_link8"
    },
    {
      "attempt": 11,
      "attempt_global": 11,
      "index": 10,
      "joint_names": [
        "panda_joint1",
        "panda_joint2",
        "panda_joint3",
        "panda_joint4",
        "panda_joint5",
        "panda_joint6",
        "panda_joint7"
      ],
      "joint_positions": [
        2.8973,
        -0.5332649244162315,
        -2.855502089776246,
        -2.4439414733338087,
        -0.6743079762264923,
        2.909752649450534,
        -0.021360883997748627
      ],
      "pass_index": 0,
      "pass_seed": 2001007,
      "sampled_yaw_rad": -1.4712886300657804,
      "target_point": {
        "x": 0.4474597967895352,
        "y": 0.07414919572539724,
        "z": 0.09897098197944355
      },
      "tip_link": "panda_link8"
    },
    {
      "attempt": 12,
      "attempt_global": 12,
      "index": 11,
      "joint_names": [
        "panda_joint1",
        "panda_joint2",
        "panda_joint3",
        "panda_joint4",
        "panda_joint5",
        "panda_joint6",
        "panda_joint7"
      ],
      "joint_positions": [
        -1.2242781627862898,
        1.310159056676523,
        1.1751650360858454,
        -2.350871278368414,
        -1.6588570407216754,
        2.0330348109439726,
        0.4085130411469409
      ],
      "pass_index": 0,
      "pass_seed": 2001007,
      "sampled_yaw_rad": -1.4712886300657804,
      "target_point": {
        "x": 0.4474597967895352,
        "y": 0.07414919572539724,
        "z": 0.09897098197944355
      },
      "tip_link": "panda_link8"
    },
    {
      "attempt": 13,
      "attempt_global": 13,
      "index": 12,
      "joint_names": [
        "panda_joint1",
        "panda_joint2",
        "panda_joint3",
        "panda_joint4",
        "panda_joint5",
        "panda_joint6",
        "panda_joint7"
      ],
      "joint_positions": [
        2.7372773420395795,
        -0.570240572011395,
        -2.72254707555194,
        -2.419438301988847,
        -0.867164291234592,
        2.84938180284012,
        0.1138482975868201
      ],
      "pass_index": 0,
      "pass_seed": 2001007,
      "sampled_yaw_rad": -1.4712886300657804,
      "target_point": {
        "x": 0.4474597967895352,
        "y": 0.07414919572539724,
        "z": 0.09897098197944355
      },
      "tip_link": "panda_link8"
    },
    {
      "attempt": 14,
      "attempt_global": 14,
      "index": 13,
      "joint_names": [
        "panda_joint1",
        "panda_joint2",
        "panda_joint3",
        "panda_joint4",
        "panda_joint5",
        "panda_joint6",
        "panda_joint7"
      ],
      "joint_positions": [
        2.873697505736263,
        -0.5378341347684915,
        -2.8365474760159026,
        -2.440290690372306,
        -0.7050307642912411,
        2.901893821374533,
        0.0006679810314298091
      ],
      "pass_index": 0,
      "pass_seed": 2001007,
      "sampled_yaw_rad": -1.4712886300657804,
      "target_point": {
        "x": 0.4474597967895352,
        "y": 0.07414919572539724,
        "z": 0.09897098197944355
      },
      "tip_link": "panda_link8"
    },
    {
      "attempt": 15,
      "attempt_global": 15,
      "index": 14,
      "joint_names": [
        "panda_joint1",
        "panda_joint2",
        "panda_joint3",
        "panda_joint4",
        "panda_joint5",
        "panda_joint6",
        "panda_joint7"
      ],
      "joint_positions": [
        2.71958549349522,
        -0.575271217159988,
        -2.707275910344734,
        -2.416817653439602,
        -0.8865035031456129,
        2.8416632214982926,
        0.12690075022313016
      ],
      "pass_index": 0,
      "pass_seed": 2001007,
      "sampled_yaw_rad": -1.4712886300657804,
      "target_point": {
        "x": 0.4474597967895352,
        "y": 0.07414919572539724,
        "z": 0.09897098197944355
      },
      "tip_link": "panda_link8"
    },
    {
      "attempt": 16,
      "attempt_global": 16,
      "index": 15,
      "joint_names": [
        "panda_joint1",
        "panda_joint2",
        "panda_joint3",
        "panda_joint4",
        "panda_joint5",
        "panda_joint6",
        "panda_joint7"
      ],
      "joint_positions": [
        -0.24459845777575354,
        0.5333200586214518,
        0.2863351309280145,
        -2.443896097886573,
        -0.6747035729691238,
        2.9096543975219724,
        0.6779400389011557
      ],
      "pass_index": 0,
      "pass_seed": 2001007,
      "sampled_yaw_rad": -0.7722715205262904,
      "target_point": {
        "x": 0.4474597967895352,
        "y": 0.07414919572539724,
        "z": 0.09897098197944355
      },
      "tip_link": "panda_link8"
    },
    {
      "attempt": 17,
      "attempt_global": 17,
      "index": 16,
      "joint_names": [
        "panda_joint1",
        "panda_joint2",
        "panda_joint3",
        "panda_joint4",
        "panda_joint5",
        "panda_joint6",
        "panda_joint7"
      ],
      "joint_positions": [
        -0.11071285752626144,
        0.5124742133558597,
        0.18390544841439305,
        -2.463785346259238,
        -0.4829036291933484,
        2.947269067709293,
        0.5378609066009247
      ],
      "pass_index": 0,
      "pass_seed": 2001007,
      "sampled_yaw_rad": -0.7722715205262904,
      "target_point": {
        "x": 0.4474597967895352,
        "y": 0.07414919572539724,
        "z": 0.09897098197944355
      },
      "tip_link": "panda_link8"
    },
    {
      "attempt": 18,
      "attempt_global": 18,
      "index": 17,
      "joint_names": [
        "panda_joint1",
        "panda_joint2",
        "panda_joint3",
        "panda_joint4",
        "panda_joint5",
        "panda_joint6",
        "panda_joint7"
      ],
      "joint_positions": [
        -0.09323199272034362,
        0.5103605098702482,
        0.17121542973082146,
        -2.466164441309903,
        -0.45552809918667403,
        2.9512607592412485,
        0.5176101491881486
      ],
      "pass_index": 0,
      "pass_seed": 2001007,
      "sampled_yaw_rad": -0.7722715205262904,
      "target_point": {
        "x": 0.4474597967895352,
        "y": 0.07414919572539724,
        "z": 0.09897098197944355
      },
      "tip_link": "panda_link8"
    },
    {
      "attempt": 19,
      "attempt_global": 19,
      "index": 18,
      "joint_names": [
        "panda_joint1",
        "panda_joint2",
        "panda_joint3",
        "panda_joint4",
        "panda_joint5",
        "panda_joint6",
        "panda_joint7"
      ],
      "joint_positions": [
        -0.3012944250726297,
        0.5447931977130447,
        0.3322839729328919,
        -2.435122817368722,
        -0.7470566080186014,
        2.8901599681018415,
        0.7295620346255253
      ],
      "pass_index": 0,
      "pass_seed": 2001007,
      "sampled_yaw_rad": -0.7722715205262904,
      "target_point": {
        "x": 0.4474597967895352,
        "y": 0.07414919572539724,
        "z": 0.09897098197944355
      },
      "tip_link": "panda_link8"
    },
    {
      "attempt": 20,
      "attempt_global": 20,
      "index": 19,
      "joint_names": [
        "panda_joint1",
        "panda_joint2",
        "panda_joint3",
        "panda_joint4",
        "panda_joint5",
        "panda_joint6",
        "panda_joint7"
      ],
      "joint_positions": [
        -0.4229006243334942,
        0.5755308146633621,
        0.4350905750744666,
        -2.416686025202769,
        -0.8874711745062303,
        2.8412676585820433,
        0.8265678697180943
      ],
      "pass_index": 0,
      "pass_seed": 2001007,
      "sampled_yaw_rad": -0.7722715205262904,
      "target_point": {
        "x": 0.4474597967895352,
        "y": 0.07414919572539724,
        "z": 0.09897098197944355
      },
      "tip_link": "panda_link8"
    },
    {
      "attempt": 21,
      "attempt_global": 21,
      "index": 20,
      "joint_names": [
        "panda_joint1",
        "panda_joint2",
        "panda_joint3",
        "panda_joint4",
        "panda_joint5",
        "panda_joint6",
        "panda_joint7"
      ],
      "joint_positions": [
        -0.24266449751336489,
        0.8568033728097973,
        0.5802865108143167,
        -1.9229529390825815,
        2.3343867781678833,
        3.7525,
        -1.72286467578805
      ],
      "pass_index": 0,
      "pass_seed": 2001007,
      "sampled_yaw_rad": -0.23689138836069956,
      "target_point": {
        "x": 0.4474597967895352,
        "y": 0.07414919572539724,
        "z": 0.09897098197944355
      },
      "tip_link": "panda_link8"
    },
    {
      "attempt": 22,
      "attempt_global": 22,
      "index": 21,
      "joint_names": [
        "panda_joint1",
        "panda_joint2",
        "panda_joint3",
        "panda_joint4",
        "panda_joint5",
        "panda_joint6",
        "panda_joint7"
      ],
      "joint_positions": [
        -0.12009879131318049,
        0.8149400863158979,
        0.41483641068197363,
        -1.889400843669262,
        2.5565724599224096,
        3.701499704661578,
        -1.9088053314800737
      ],
      "pass_index": 0,
      "pass_seed": 2001007,
      "sampled_yaw_rad": -0.23689138836069956,
      "target_point": {
        "x": 0.4474597967895352,
        "y": 0.07414919572539724,
        "z": 0.09897098197944355
      },
      "tip_link": "panda_link8"
    },
    {
      "attempt": 23,
      "attempt_global": 23,
      "index": 22,
      "joint_names": [
        "panda_joint1",
        "panda_joint2",
        "panda_joint3",
        "panda_joint4",
        "panda_joint5",
        "panda_joint6",
        "panda_joint7"
      ],
      "joint_positions": [
        1.7577601587194156,
        -1.7628,
        -1.8435640797888517,
        -2.3698877731248946,
        -1.8996691052608932,
        1.6184593636660116,
        1.5685039315657996
      ],
      "pass_index": 0,
      "pass_seed": 2001007,
      "sampled_yaw_rad": -0.23689138836069956,
      "target_point": {
        "x": 0.4474597967895352,
        "y": 0.07414919572539724,
        "z": 0.09897098197944355
      },
      "tip_link": "panda_link8"
    },
    {
      "attempt": 24,
      "attempt_global": 24,
      "index": 23,
      "joint_names": [
        "panda_joint1",
        "panda_joint2",
        "panda_joint3",
        "panda_joint4",
        "panda_joint5",
        "panda_joint6",
        "panda_joint7"
      ],
      "joint_positions": [
        -0.22698193992297114,
        0.8502933641360125,
        0.5596142263766644,
        -1.918524059639808,
        2.3615997702981475,
        3.7447460032281072,
        -1.744923342951548
      ],
      "pass_index": 0,
      "pass_seed": 2001007,
      "sampled_yaw_rad": -0.23689138836069956,
      "target_point": {
        "x": 0.4474597967895352,
        "y": 0.07414919572539724,
        "z": 0.09897098197944355
      },
      "tip_link": "panda_link8"
    },
    {
      "attempt": 25,
      "attempt_global": 25,
      "index": 24,
      "joint_names": [
        "panda_joint1",
        "panda_joint2",
        "panda_joint3",
        "panda_joint4",
        "panda_joint5",
        "panda_joint6",
        "panda_joint7"
      ],
      "joint_positions": [
        -0.2138461854807221,
        0.8451201127747822,
        0.5421916090400966,
        -1.9148265760017922,
        2.38466483561077,
        3.738542412045127,
        -1.7638039882267849
      ],
      "pass_index": 0,
      "pass_seed": 2001007,
      "sampled_yaw_rad": -0.23689138836069956,
      "target_point": {
        "x": 0.4474597967895352,
        "y": 0.07414919572539724,
        "z": 0.09897098197944355
      },
      "tip_link": "panda_link8"
    },
    {
      "attempt": 26,
      "attempt_global": 26,
      "index": 25,
      "joint_names": [
        "panda_joint1",
        "panda_joint2",
        "panda_joint3",
        "panda_joint4",
        "panda_joint5",
        "panda_joint6",
        "panda_joint7"
      ],
      "joint_positions": [
        -2.4227985720419856,
        -0.5664151836276466,
        2.734524665785366,
        -2.4215249777307575,
        0.8516570127477265,
        2.8553204005000703,
        0.7005081372180463
      ],
      "pass_index": 0,
      "pass_seed": 2001007,
      "sampled_yaw_rad": 0.3766589261053035,
      "target_point": {
        "x": 0.4474597967895352,
        "y": 0.07414919572539724,
        "z": 0.09897098197944355
      },
      "tip_link": "panda_link8"
    },
    {
      "attempt": 27,
      "attempt_global": 27,
      "index": 26,
      "joint_names": [
        "panda_joint1",
        "panda_joint2",
        "panda_joint3",
        "panda_joint4",
        "panda_joint5",
        "panda_joint6",
        "panda_joint7"
      ],
      "joint_positions": [
        -2.212915899098507,
        -0.6392324280766919,
        2.5486666881578395,
        -2.392226289453149,
        1.0653908284269915,
        2.7507198913871,
        0.5631184200429061
      ],
      "pass_index": 0,
      "pass_seed": 2001007,
      "sampled_yaw_rad": 0.3766589261053035,
      "target_point": {
        "x": 0.4474597967895352,
        "y": 0.07414919572539724,
        "z": 0.09897098197944355
      },
      "tip_link": "panda_link8"
    },
    {
      "attempt": 28,
      "attempt_global": 28,
      "index": 27,
      "joint_names": [
        "panda_joint1",
        "panda_joint2",
        "panda_joint3",
        "panda_joint4",
        "panda_joint5",
        "panda_joint6",
        "panda_joint7"
      ],
      "joint_positions": [
        -2.4621834494227213,
        -0.5562794986603261,
        2.7679593530785462,
        -2.427485447555326,
        0.8066646974470387,
        2.871369697199355,
        0.7314841975254918
      ],
      "pass_index": 0,
      "pass_seed": 2001007,
      "sampled_yaw_rad": 0.3766589261053035,
      "target_point": {
        "x": 0.4474597967895352,
        "y": 0.07414919572539724,
        "z": 0.09897098197944355
      },
      "tip_link": "panda_link8"
    },
    {
      "attempt": 29,
      "attempt_global": 29,
      "index": 28,
      "joint_names": [
        "panda_joint1",
        "panda_joint2",
        "panda_joint3",
        "panda_joint4",
        "panda_joint5",
        "panda_joint6",
        "panda_joint7"
      ],
      "joint_positions": [
        -2.335001113617173,
        -0.5926737782679263,
        2.6581876559229376,
        -2.408693270405816,
        0.9457458400625607,
        2.8156968655555175,
        0.6377097950505068
      ],
      "pass_index": 0,
      "pass_seed": 2001007,
      "sampled_yaw_rad": 0.3766589261053035,
      "target_point": {
        "x": 0.4474597967895352,
        "y": 0.07414919572539724,
        "z": 0.09897098197944355
      },
      "tip_link": "panda_link8"
    },
    {
      "attempt": 30,
      "attempt_global": 30,
      "index": 29,
      "joint_names": [
        "panda_joint1",
        "panda_joint2",
        "panda_joint3",
        "panda_joint4",
        "panda_joint5",
        "panda_joint6",
        "panda_joint7"
      ],
      "joint_positions": [
        -2.3063262676973695,
        -0.6024678993002086,
        2.632781386952469,
        -2.4046693890005275,
        0.9748714904193938,
        2.801532204212262,
        0.6189316111374393
      ],
      "pass_index": 0,
      "pass_seed": 2001007,
      "sampled_yaw_rad": 0.3766589261053035,
      "target_point": {
        "x": 0.4474597967895352,
        "y": 0.07414919572539724,
        "z": 0.09897098197944355
      },
      "tip_link": "panda_link8"
    },
    {
      "attempt": 31,
      "attempt_global": 31,
      "index": 30,
      "joint_names": [
        "panda_joint1",
        "panda_joint2",
        "panda_joint3",
        "panda_joint4",
        "panda_joint5",
        "panda_joint6",
        "panda_joint7"
      ],
      "joint_positions": [
        2.8926178420080784,
        -0.5341298634377692,
        -2.8517588432509724,
        -2.4432345734620613,
        -0.6804292360448428,
        2.908225316248184,
        2.67828923962032
      ],
      "pass_index": 0,
      "pass_seed": 2001007,
      "sampled_yaw_rad": 1.2239721400708978,
      "target_point": {
        "x": 0.4474597967895352,
        "y": 0.07414919572539724,
        "z": 0.09897098197944355
      },
      "tip_link": "panda_link8"
    },
    {
      "attempt": 32,
      "attempt_global": 32,
      "index": 31,
      "joint_names": [
        "panda_joint1",
        "panda_joint2",
        "panda_joint3",
        "panda_joint4",
        "panda_joint5",
        "panda_joint6",
        "panda_joint7"
      ],
      "joint_positions": [
        -2.608375114404479,
        -0.5262369404043743,
        2.8866567402970778,
        -2.450007591058766,
        0.6208758580907645,
        2.922098438271346,
        1.7111139944300509
      ],
      "pass_index": 0,
      "pass_seed": 2001007,
      "sampled_yaw_rad": 1.2239721400708978,
      "target_point": {
        "x": 0.4474597967895352,
        "y": 0.07414919572539724,
        "z": 0.09897098197944355
      },
      "tip_link": "panda_link8"
    },
    {
      "attempt": 33,
      "attempt_global": 33,
      "index": 32,
      "joint_names": [
        "panda_joint1",
        "panda_joint2",
        "panda_joint3",
        "panda_joint4",
        "panda_joint5",
        "panda_joint6",
        "panda_joint7"
      ],
      "joint_positions": [
        2.7019613423542737,
        -0.5804927189569002,
        -2.691966474671695,
        -2.4142345895611976,
        -0.9054370021707279,
        2.833756795369818,
        2.834823628425353
      ],
      "pass_index": 0,
      "pass_seed": 2001007,
      "sampled_yaw_rad": 1.2239721400708978,
      "target_point": {
        "x": 0.4474597967895352,
        "y": 0.07414919572539724,
        "z": 0.09897098197944355
      },
      "tip_link": "panda_link8"
    },
    {
      "attempt": 34,
      "attempt_global": 34,
      "index": 33,
      "joint_names": [
        "panda_joint1",
        "panda_joint2",
        "panda_joint3",
        "panda_joint4",
        "panda_joint5",
        "panda_joint6",
        "panda_joint7"
      ],
      "joint_positions": [
        2.7935103289797563,
        -0.5555734303188992,
        -2.770389990486223,
        -2.4279258786038302,
        -0.8032903431223621,
        2.872505995184558,
        2.7652414720983756
      ],
      "pass_index": 0,
      "pass_seed": 2001007,
      "sampled_yaw_rad": 1.2239721400708978,
      "target_point": {
        "x": 0.4474597967895352,
        "y": 0.07414919572539724,
        "z": 0.09897098197944355
      },
      "tip_link": "panda_link8"
    },
    {
      "attempt": 35,
      "attempt_global": 35,
      "index": 34,
      "joint_names": [
        "panda_joint1",
        "panda_joint2",
        "panda_joint3",
        "panda_joint4",
        "panda_joint5",
        "panda_joint6",
        "panda_joint7"
      ],
      "joint_positions": [
        2.839045968983647,
        -0.5450661399987576,
        -2.808278558985085,
        -2.4349288778183027,
        -0.7486023278153048,
        2.8897057062206155,
        2.7268986661909334
      ],
      "pass_index": 0,
      "pass_seed": 2001007,
      "sampled_yaw_rad": 1.2239721400708978,
      "target_point": {
        "x": 0.4474597967895352,
        "y": 0.07414919572539724,
        "z": 0.09897098197944355
      },
      "tip_link": "panda_link8"
    },
    {
      "attempt": 36,
      "attempt_global": 36,
      "index": 35,
      "joint_names": [
        "panda_joint1",
        "panda_joint2",
        "panda_joint3",
        "panda_joint4",
        "panda_joint5",
        "panda_joint6",
        "panda_joint7"
      ],
      "joint_positions": [
        -1.3838314970333057,
        1.7627969342644458,
        1.2980279661535628,
        -2.3698875498174274,
        -1.899667487224577,
        1.618462230481554,
        -2.8103952168278217
      ],
      "pass_index": 0,
      "pass_seed": 2001007,
      "sampled_yaw_rad": 1.66739406661127,
      "target_point": {
        "x": 0.4474597967895352,
        "y": 0.07414919572539724,
        "z": 0.09897098197944355
      },
      "tip_link": "panda_link8"
    },
    {
      "attempt": 37,
      "attempt_global": 37,
      "index": 36,
      "joint_names": [
        "panda_joint1",
        "panda_joint2",
        "panda_joint3",
        "panda_joint4",
        "panda_joint5",
        "panda_joint6",
        "panda_joint7"
      ],
      "joint_positions": [
        -0.7574892156681851,
        0.7223780729713816,
        0.7381698897058713,
        -2.373890734792543,
        -1.2075139190625928,
        2.6455031917183685,
        -2.8265933767821925
      ],
      "pass_index": 0,
      "pass_seed": 2001007,
      "sampled_yaw_rad": 1.66739406661127,
      "target_point": {
        "x": 0.4474597967895352,
        "y": 0.07414919572539724,
        "z": 0.09897098197944355
      },
      "tip_link": "panda_link8"
    },
    {
      "attempt": 38,
      "attempt_global": 38,
      "index": 37,
      "joint_names": [
        "panda_joint1",
        "panda_joint2",
        "panda_joint3",
        "panda_joint4",
        "panda_joint5",
        "panda_joint6",
        "panda_joint7"
      ],
      "joint_positions": [
        -1.3695112420530207,
        1.715514396846319,
        1.2892880532742625,
        -2.3670561492582403,
        -1.8739530040231136,
        1.660100660160713,
        -2.7990558611790566
      ],
      "pass_index": 0,
      "pass_seed": 2001007,
      "sampled_yaw_rad": 1.66739406661127,
      "target_point": {
        "x": 0.4474597967895352,
        "y": 0.07414919572539724,
        "z": 0.09897098197944355
      },
      "tip_link": "panda_link8"
    },
    {
      "attempt": 39,
      "attempt_global": 39,
      "index": 38,
      "joint_names": [
        "panda_joint1",
        "panda_joint2",
        "panda_joint3",
        "panda_joint4",
        "panda_joint5",
        "panda_joint6",
        "panda_joint7"
      ],
      "joint_positions": [
        -1.316452450371744,
        1.5505556700580159,
        1.2518981408447418,
        -2.3586616660804003,
        -1.7863941125792349,
        1.8084739039598818,
        -2.765995697705166
      ],
      "pass_index": 0,
      "pass_seed": 2001007,
      "sampled_yaw_rad": 1.66739406661127,
      "target_point": {
        "x": 0.4474597967895352,
        "y": 0.07414919572539724,
        "z": 0.09897098197944355
      },
      "tip_link": "panda_link8"
    },
    {
      "attempt": 40,
      "attempt_global": 40,
      "index": 39,
      "joint_names": [
        "panda_joint1",
        "panda_joint2",
        "panda_joint3",
        "panda_joint4",
        "panda_joint5",
        "panda_joint6",
        "panda_joint7"
      ],
      "joint_positions": [
        -1.3478541615955024,
        1.6460419935842323,
        1.2748769404250366,
        -2.363243634154237,
        -1.8367665244211195,
        1.7220122262958921,
        -2.783915565937808
      ],
      "pass_index": 0,
      "pass_seed": 2001007,
      "sampled_yaw_rad": 1.66739406661127,
      "target_point": {
        "x": 0.4474597967895352,
        "y": 0.07414919572539724,
        "z": 0.09897098197944355
      },
      "tip_link": "panda_link8"
    },
    {
      "attempt": 41,
      "attempt_global": 41,
      "index": 40,
      "joint_names": [
        "panda_joint1",
        "panda_joint2",
        "panda_joint3",
        "panda_joint4",
        "panda_joint5",
        "panda_joint6",
        "panda_joint7"
      ],
      "joint_positions": [
        0.6949050802169582,
        0.5601545643577853,
        -0.38672247668419296,
        -2.4251277978717924,
        0.8245941989200591,
        2.865178198942031,
        2.5673042876830587
      ],
      "pass_index": 0,
      "pass_seed": 2001007,
      "sampled_yaw_rad": 2.2248862809817984,
      "target_point": {
        "x": 0.4474597967895352,
        "y": 0.07414919572539724,
        "z": 0.09897098197944355
      },
      "tip_link": "panda_link8"
    },
    {
      "attempt": 42,
      "attempt_global": 42,
      "index": 41,
      "joint_names": [
        "panda_joint1",
        "panda_joint2",
        "panda_joint3",
        "panda_joint4",
        "panda_joint5",
        "panda_joint6",
        "panda_joint7"
      ],
      "joint_positions": [
        0.5412784033378567,
        0.5276088577782914,
        -0.26123104009397347,
        -2.4487774167812892,
        0.6319852319627222,
        2.9196629195729407,
        2.7039657454552852
      ],
      "pass_index": 0,
      "pass_seed": 2001007,
      "sampled_yaw_rad": 2.2248862809817984,
      "target_point": {
        "x": 0.4474597967895352,
        "y": 0.07414919572539724,
        "z": 0.09897098197944355
      },
      "tip_link": "panda_link8"
    },
    {
      "attempt": 43,
      "attempt_global": 43,
      "index": 42,
      "joint_names": [
        "panda_joint1",
        "panda_joint2",
        "panda_joint3",
        "panda_joint4",
        "panda_joint5",
        "panda_joint6",
        "panda_joint7"
      ],
      "joint_positions": [
        0.7402938110640406,
        0.5723584791707897,
        -0.42554237202393375,
        -2.418319039696588,
        0.8754461371916397,
        2.8461192122658923,
        2.5325842335238637
      ],
      "pass_index": 0,
      "pass_seed": 2001007,
      "sampled_yaw_rad": 2.2248862809817984,
      "target_point": {
        "x": 0.4474597967895352,
        "y": 0.07414919572539724,
        "z": 0.09897098197944355
      },
      "tip_link": "panda_link8"
    },
    {
      "attempt": 44,
      "attempt_global": 44,
      "index": 43,
      "joint_names": [
        "panda_joint1",
        "panda_joint2",
        "panda_joint3",
        "panda_joint4",
        "panda_joint5",
        "panda_joint6",
        "panda_joint7"
      ],
      "joint_positions": [
        0.8803223109852248,
        0.6192189164505645,
        -0.5491417272629189,
        -2.398535378360665,
        1.0192934445954493,
        2.7779556906280023,
        2.4392468745433034
      ],
      "pass_index": 0,
      "pass_seed": 2001007,
      "sampled_yaw_rad": 2.2248862809817984,
      "target_point": {
        "x": 0.4474597967895352,
        "y": 0.07414919572539724,
        "z": 0.09897098197944355
      },
      "tip_link": "panda_link8"
    },
    {
      "attempt": 45,
      "attempt_global": 45,
      "index": 44,
      "joint_names": [
        "panda_joint1",
        "panda_joint2",
        "panda_joint3",
        "panda_joint4",
        "panda_joint5",
        "panda_joint6",
        "panda_joint7"
      ],
      "joint_positions": [
        0.6801691151791457,
        0.5564666685412861,
        -0.37427292736678514,
        -2.427368963108047,
        0.8075524491251819,
        2.8710694244255097,
        2.579095103090537
      ],
      "pass_index": 0,
      "pass_seed": 2001007,
      "sampled_yaw_rad": 2.2248862809817984,
      "target_point": {
        "x": 0.4474597967895352,
        "y": 0.07414919572539724,
        "z": 0.09897098197944355
      },
      "tip_link": "panda_link8"
    },
    {
      "attempt": 46,
      "attempt_global": 46,
      "index": 45,
      "joint_names": [
        "panda_joint1",
        "panda_joint2",
        "panda_joint3",
        "panda_joint4",
        "panda_joint5",
        "panda_joint6",
        "panda_joint7"
      ],
      "joint_positions": [
        1.9526445199227147,
        -1.2334300357875099,
        -1.9980224184688111,
        -2.3496717693966165,
        -1.6162777262798405,
        2.1069025796578127,
        -1.732175964569181
      ],
      "pass_index": 0,
      "pass_seed": 2001007,
      "sampled_yaw_rad": 2.6666430256717577,
      "target_point": {
        "x": 0.4474597967895352,
        "y": 0.07414919572539724,
        "z": 0.09897098197944355
      },
      "tip_link": "panda_link8"
    },
    {
      "attempt": 47,
      "attempt_global": 47,
      "index": 46,
      "joint_names": [
        "panda_joint1",
        "panda_joint2",
        "panda_joint3",
        "panda_joint4",
        "panda_joint5",
        "panda_joint6",
        "panda_joint7"
      ],
      "joint_positions": [
        1.9607805014913722,
        -1.2168684069463693,
        -2.0054036668529043,
        -2.3495082756854213,
        -1.6068606103880363,
        2.123001733983565,
        -1.7315555092733408
      ],
      "pass_index": 0,
      "pass_seed": 2001007,
      "sampled_yaw_rad": 2.6666430256717577,
      "target_point": {
        "x": 0.4474597967895352,
        "y": 0.07414919572539724,
        "z": 0.09897098197944355
      },
      "tip_link": "panda_link8"
    },
    {
      "attempt": 48,
      "attempt_global": 48,
      "index": 47,
      "joint_names": [
        "panda_joint1",
        "panda_joint2",
        "panda_joint3",
        "panda_joint4",
        "panda_joint5",
        "panda_joint6",
        "panda_joint7"
      ],
      "joint_positions": [
        2.012346508576317,
        -1.1207181808280018,
        -2.052848962781279,
        -2.349323492133038,
        -1.5500044391968235,
        2.217657942471546,
        -1.730853604116159
      ],
      "pass_index": 0,
      "pass_seed": 2001007,
      "sampled_yaw_rad": 2.6666430256717577,
      "target_point": {
        "x": 0.4474597967895352,
        "y": 0.07414919572539724,
        "z": 0.09897098197944355
      },
      "tip_link": "panda_link8"
    },
    {
      "attempt": 49,
      "attempt_global": 49,
      "index": 48,
      "joint_names": [
        "panda_joint1",
        "panda_joint2",
        "panda_joint3",
        "panda_joint4",
        "panda_joint5",
        "panda_joint6",
        "panda_joint7"
      ],
      "joint_positions": [
        1.916218613585509,
        -1.3126593860998534,
        -1.96546327111949,
        -2.3509268835660877,
        -1.6602204077165927,
        2.030645122135358,
        -1.7369341596095809
      ],
      "pass_index": 0,
      "pass_seed": 2001007,
      "sampled_yaw_rad": 2.6666430256717577,
      "target_point": {
        "x": 0.4474597967895352,
        "y": 0.07414919572539724,
        "z": 0.09897098197944355
      },
      "tip_link": "panda_link8"
    },
    {
      "attempt": 50,
      "attempt_global": 50,
      "index": 49,
      "joint_names": [
        "panda_joint1",
        "panda_joint2",
        "panda_joint3",
        "panda_joint4",
        "panda_joint5",
        "panda_joint6",
        "panda_joint7"
      ],
      "joint_positions": [
        1.8903836697006724,
        -1.3742000239289287,
        -1.9429782054642202,
        -2.352383819015814,
        -1.6934021109167794,
        1.9722294589140532,
        -1.7425209902731638
      ],
      "pass_index": 0,
      "pass_seed": 2001007,
      "sampled_yaw_rad": 2.6666430256717577,
      "target_point": {
        "x": 0.4474597967895352,
        "y": 0.07414919572539724,
        "z": 0.09897098197944355
      },
      "tip_link": "panda_link8"
    }
  ]
}